pyredact/__init__.py
pyredact/anonymizer.py
pyredact/detector.py
pyredact/main.py
pyredact/regex_patterns.py
pyredact/report_generator.py
pyredact_mv-1.0.1.dist-info/METADATA
pyredact_mv-1.0.1.dist-info/WHEEL
pyredact_mv-1.0.1.dist-info/entry_points.txt
pyredact_mv-1.0.1.dist-info/top_level.txt
pyredact_mv-1.0.1.dist-info/RECORD
