Metadata-Version: 2.4
Name: pyredact-mv
Version: 1.0.1
Summary: A professional CLI tool to detect and de-identify PII from CSV files.
Author-email: MonishV0017 <monishv0017@gmail.com>
Project-URL: Homepage, https://github.com/MonishV0017/pii-redactor
Classifier: Programming Language :: Python :: 3
Classifier: Operating System :: OS Independent
Requires-Python: >=3.8
Requires-Dist: pandas
Requires-Dist: typer
Requires-Dist: rich
Requires-Dist: chardet
